willing_zg/__init__.py
willing_zg/all_components.py
willing_zg/backend_images.py
willing_zg/chat.py
willing_zg/django_willing_zg.py
willing_zg/get_env.py
willing_zg/google_analytics.py
willing_zg/idle_session_handler.py
willing_zg/resources/ChatWidget.js
willing_zg/resources/Dockerfile
willing_zg/resources/Dockerfile.local
willing_zg/resources/IdleSessionHandler.js
willing_zg/resources/__init__.py
willing_zg/resources/chat.js
willing_zg/resources/getEnv.js
willing_zg/resources/google-analytics.js
willing_zg/resources/google.js
willing_zg/resources/mailer.py
willing_zg/resources/requirements.deploy.txt
willing_zg/resources/tokens.js
willing_zg/tokens.py
willing_zg-1.4.0.dist-info/WHEEL
willing_zg-1.4.0.dist-info/METADATA
willing_zg-1.4.0.dist-info/RECORD
