Metadata-Version: 2.1
Name: willing-zg
Version: 1.4.0
Summary: 
Author: Bequest, Inc.
Author-email: oss@willing.com
Requires-Python: >=3.7,<4.0
Classifier: Programming Language :: Python :: 3
Classifier: Programming Language :: Python :: 3.10
Classifier: Programming Language :: Python :: 3.7
Classifier: Programming Language :: Python :: 3.8
Classifier: Programming Language :: Python :: 3.9
Requires-Dist: boto3 (>=1.14.59,<2.0.0)
Requires-Dist: zygoat (>=1.1.0,<2.0.0)
